git_manage/__init__.py
git_manage/git_tools.py
git_manage/url.py
git_manage/support/config.yaml
git_manage-0.0.20.data/scripts/gitman
git_manage-0.0.20.data/scripts/gitman.bat
git_manage-0.0.20.data/scripts/gitpush
git_manage-0.0.20.dist-info/licenses/LICENSE
git_manage-0.0.20.dist-info/METADATA
git_manage-0.0.20.dist-info/WHEEL
git_manage-0.0.20.dist-info/top_level.txt
git_manage-0.0.20.dist-info/RECORD
